aiofreepybox/.gitignore
aiofreepybox/__init__.py
aiofreepybox/access.py
aiofreepybox/aiofreepybox.py
aiofreepybox/app_auth
aiofreepybox/app_auth.bak
aiofreepybox/constants.py
aiofreepybox/exceptions.py
aiofreepybox/freebox_certificates.pem
aiofreepybox/__pycache__/__init__.cpython-36.pyc
aiofreepybox/__pycache__/access.cpython-36.pyc
aiofreepybox/__pycache__/aiofreepybox.cpython-36.pyc
aiofreepybox/__pycache__/constants.cpython-36.pyc
aiofreepybox/__pycache__/exceptions.cpython-36.pyc
aiofreepybox/__pycache__/freepybox.cpython-36.pyc
aiofreepybox/api/.gitignore
aiofreepybox/api/__init__.py
aiofreepybox/api/call.py
aiofreepybox/api/connection.py
aiofreepybox/api/dhcp.py
aiofreepybox/api/fs.py
aiofreepybox/api/lan.py
aiofreepybox/api/nat.py
aiofreepybox/api/switch.py
aiofreepybox/api/system.py
aiofreepybox/api/wifi.py
aiofreepybox/api/__pycache__/__init__.cpython-36.pyc
aiofreepybox/api/__pycache__/call.cpython-36.pyc
aiofreepybox/api/__pycache__/connection.cpython-36.pyc
aiofreepybox/api/__pycache__/dhcp.cpython-36.pyc
aiofreepybox/api/__pycache__/fs.cpython-36.pyc
aiofreepybox/api/__pycache__/fsnav.cpython-36.pyc
aiofreepybox/api/__pycache__/lan.cpython-36.pyc
aiofreepybox/api/__pycache__/nat.cpython-36.pyc
aiofreepybox/api/__pycache__/switch.cpython-36.pyc
aiofreepybox/api/__pycache__/system.cpython-36.pyc
aiofreepybox/api/__pycache__/wifi.cpython-36.pyc
aiofreepybox-0.0.8.dist-info/LICENSE.txt
aiofreepybox-0.0.8.dist-info/METADATA
aiofreepybox-0.0.8.dist-info/WHEEL
aiofreepybox-0.0.8.dist-info/top_level.txt
aiofreepybox-0.0.8.dist-info/RECORD
