Metadata-Version: 2.1
Name: aiofreepybox
Version: 0.0.8
Summary: Provides asynchronous authentication and access to Freebox servers
Home-page: https://github.com/stilllman/aiofreepybox/tree/aiofreepybox
Author: stilllman
Author-email: luc_touraille@yahoo.fr
License: UNKNOWN
Keywords: freebox async
Platform: UNKNOWN
Classifier: Programming Language :: Python
Classifier: Development Status :: 3 - Alpha
Classifier: License :: OSI Approved :: GNU General Public License (GPL)
Classifier: Programming Language :: Python :: 3
Classifier: Programming Language :: Python :: 3.5
Classifier: Programming Language :: Python :: 3.6
Classifier: Framework :: AsyncIO
Classifier: Intended Audience :: Developers
Classifier: Intended Audience :: System Administrators
Classifier: Topic :: Home Automation
Requires-Dist: aiohttp (<4,>=3)
